tests/__init__.py
tests/test_action_layer.py
tests/test_basic_cell.py
tests/test_feedforward.py
tests/test_model_utils.py
tests/test_montecarlo.py
tests/test_planner_minimax.py
tests/test_planner_pathwise.py
tests/test_reparameterization_cell.py
tests/test_reparameterization_model.py
tests/test_state_layer.py
tests/test_valuefn.py
tf_mdp-0.5.5.data/scripts/tfmdp
tfmdp/__init__.py
tfmdp/utils.py
tfmdp/model/__init__.py
tfmdp/model/utils.py
tfmdp/model/cell/__init__.py
tfmdp/model/cell/basic_cell.py
tfmdp/model/cell/reparameterization_cell.py
tfmdp/model/sequential/__init__.py
tfmdp/model/sequential/montecarlo.py
tfmdp/model/sequential/mrm.py
tfmdp/model/sequential/reparameterization.py
tfmdp/planning/__init__.py
tfmdp/planning/minimax.py
tfmdp/planning/pathwise.py
tfmdp/planning/planner.py
tfmdp/policy/__init__.py
tfmdp/policy/drp.py
tfmdp/policy/feedforward.py
tfmdp/policy/layers/__init__.py
tfmdp/policy/layers/action_layer.py
tfmdp/policy/layers/state_layer.py
tfmdp/test/__init__.py
tfmdp/train/__init__.py
tfmdp/train/losses/__init__.py
tfmdp/train/optimizers/__init__.py
tfmdp/valuefn/__init__.py
tfmdp/valuefn/valuefn.py
tf_mdp-0.5.5.dist-info/LICENSE
tf_mdp-0.5.5.dist-info/METADATA
tf_mdp-0.5.5.dist-info/WHEEL
tf_mdp-0.5.5.dist-info/top_level.txt
tf_mdp-0.5.5.dist-info/RECORD
