Metadata-Version: 2.1
Name: tf-mdp
Version: 0.5.5
Summary: Probabilistic planning in continuous state-action MDPs using TensorFlow.
Home-page: https://github.com/thiagopbueno/tf-mdp
Author: Thiago P. Bueno
Author-email: thiago.pbueno@gmail.com
License: GNU General Public License v3.0
Keywords: planning,tensorflow,rddl,mdp
Platform: UNKNOWN
Classifier: Development Status :: 3 - Alpha
Classifier: Environment :: Console
Classifier: Intended Audience :: Science/Research
Classifier: License :: OSI Approved :: GNU General Public License v3 (GPLv3)
Classifier: Natural Language :: English
Classifier: Operating System :: OS Independent
Classifier: Programming Language :: Python :: 3
Classifier: Topic :: Scientific/Engineering :: Artificial Intelligence
Requires-Python: >=3.6
License-File: LICENSE
Requires-Dist: tensorflow (<2.0.0)
Requires-Dist: typing
Requires-Dist: rddlgym
Requires-Dist: tfrddlsim
